stackup_python/__init__.py
stackup_python/stackup.py
stackup_python-0.0.2.dist-info/LICENSE
stackup_python-0.0.2.dist-info/METADATA
stackup_python-0.0.2.dist-info/WHEEL
stackup_python-0.0.2.dist-info/top_level.txt
stackup_python-0.0.2.dist-info/RECORD
