Metadata-Version: 2.1
Name: stackup-python
Version: 0.0.2
Summary: Stack Up Analysis Package
Author: Utkarsh Gaikwad
Author-email: gaikwadujg@gmail.com
Keywords: stack up,tolerance,mechanical engineering
Classifier: Development Status :: 1 - Planning
Classifier: Intended Audience :: Developers
Classifier: Programming Language :: Python :: 3
Classifier: Operating System :: MacOS :: MacOS X
Classifier: Operating System :: Microsoft :: Windows
License-File: LICENSE
Requires-Dist: numpy
Requires-Dist: pyarrow
Requires-Dist: pandas
Requires-Dist: matplotlib
Requires-Dist: seaborn
Requires-Dist: fitter
